[{"id":1,"Nr":"LT404437474362483964","vardas":"Mantas","pavarde":"Malinauskas","AK":"38303220111","likutis":99.45},{"id":4,"Nr":"LT347285310054209577","vardas":"Kristina","pavarde":"Leonaviciute","AK":"48303221110","likutis":240.8},{"id":5,"Nr":"LT974250938239034203","vardas":"Petras","pavarde":"Petrauskas","AK":"38303228765","likutis":140.07999999999998},{"id":6,"Nr":"LT977549482603728346","vardas":"Karolis","pavarde":"Karoliunas","AK":"38803031234","likutis":170.76999999999998},{"id":8,"Nr":"LT234745075966241866","vardas":"Mantas","pavarde":"Kelmickis","AK":"38303220111","likutis":169.12}]